Workbook
Name CreditExposureData: 'Credit Exposure Register'!$A$7:$O$107
Name MigrationMatrix: 'Rating Migration Matrix'!$A$6:$J$14
Name SectorConcentration: 'Sector Concentration'!$A$5:$G$16
Name CounterpartyMaster: 'Counterparty Master'!$A$4:$J$24
Name RiskModelParams: 'Risk Model Parameters'!$A$4:$F$22

Sheet Credit Exposure Register
A1: CREDIT EXPOSURE REGISTER — Q3 2026
A2: As of Date: | B2: 46295 | D2: Prepared By: | E2: Credit Risk Analytics | H2: Reporting CCY: | I2: USD
A3: Approved By: | B3: Head of Credit Risk | D3: Status: | E3: FINAL | H3: Counterparties: | I3: 20
A6: Counterparty Information | E6: Trade Details | H6: Valuation | J6: Credit Risk Metrics | M6: Limits & Utilisation
A7: CP ID | B7: Legal Name | C7: Sector | D7: Country | E7: Trade Date | F7: Maturity Date | G7: Instrument | H7: Notional USD | I7: MTM USD | J7: PD 1Y | K7: LGD | L7: EAD USD | M7: Credit Limit USD | N7: Current Exposure USD | O7: Utilisation %
A8: CP001 | B8: Deutsche Bank AG | C8: Banking | D8: Germany | E8: 45736.771 | F8: 46264.771 | G8: Credit Default Swap | H8: 68000000 | I8: -1767028 | J8: 0.00083 | K8: 0.4656 | L8: 3400000 | M8: 2000000000 | N8: 3400000 | O8: 0.0017
A9: CP001 | B9: Deutsche Bank AG | C9: Banking | D9: Germany | E9: 45901.771 | F9: 46807.771 | G9: Senior Unsecured Bond | H9: 488000000 | I9: N/A | J9: 0.00083 | K9: 0.5146 | L9: 488000000 | M9: 2000000000 | N9: 488000000 | O9: 0.244
A10: CP001 | B10: Deutsche Bank AG | C10: Banking | D10: Germany | E10: 45810.771 | F10: 46222.771 | G10: Interest Rate Swap | H10: 292000000 | I10: 7921622 | J10: 0.00071 | K10: 0.4242 | L10: 8760000 | M10: 2000000000 | N10: 8760000 | O10: 0.00438
A11: CP001 | B11: Deutsche Bank AG | C11: Banking | D11: Germany | E11: 45924.771 | F11: 46922.771 | G11: Credit Default Swap | H11: 8000000 | I11: -133087 | J11: 0.00076 | K11: 0.4256 | L11: 400000 | M11: 2000000000 | N11: 400000 | O11: 0.0002
A12: CP001 | B12: Deutsche Bank AG | C12: Banking | D12: Germany | E12: 45760.771 | F12: 46155.771 | G12: Senior Unsecured Bond | H12: 386000000 | I12: N/A | J12: 0.00083 | K12: 0.507 | L12: 386000000 | M12: 2000000000 | N12: 386000000 | O12: 0.193
A13: CP002 | B13: BNP Paribas SA | C13: Banking | D13: France | E13: 45987.771 | F13: 46379.771 | G13: Senior Secured Loan | H13: 420000000 | I13: N/A | J13: 0.00116 | K13: 0.3049 | L13: 420000000 | M13: 1500000000 | N13: 420000000 | O13: 0.28
A14: CP002 | B14: BNP Paribas SA | C14: Banking | D14: France | E14: 45997.771 | F14: 46531.771 | G14: Trade Finance LC | H14: 248000000 | I14: N/A | J14: 0.00113 | K14: 0.2536 | L14: 124000000 | M14: 1500000000 | N14: 124000000 | O14: 0.082666667
A15: CP002 | B15: BNP Paribas SA | C15: Banking | D15: France | E15: 45872.771 | F15: 46734.771 | G15: Revolving Credit Fac. | H15: 286000000 | I15: N/A | J15: 0.00131 | K15: 0.3684 | L15: 214500000 | M15: 1500000000 | N15: 214500000 | O15: 0.143
A16: CP002 | B16: BNP Paribas SA | C16: Banking | D16: France | E16: 45900.771 | F16: 46458.771 | G16: Senior Secured Loan | H16: 257000000 | I16: N/A | J16: 0.00132 | K16: 0.3337 | L16: 257000000 | M16: 1500000000 | N16: 257000000 | O16: 0.17133333
A17: CP002 | B17: BNP Paribas SA | C17: Banking | D17: France | E17: 45826.771 | F17: 46306.771 | G17: Trade Finance LC | H17: 259000000 | I17: N/A | J17: 0.00111 | K17: 0.3482 | L17: 129500000 | M17: 1500000000 | N17: 129500000 | O17: 0.086333333
A18: CP003 | B18: HSBC Holdings plc | C18: Banking | D18: UK | E18: 45677.771 | F18: 46245.771 | G18: Senior Unsecured Bond | H18: 426000000 | I18: N/A | J18: 0.00073 | K18: 0.5054 | L18: 426000000 | M18: 1800000000 | N18: 426000000 | O18: 0.23666667
A19: CP003 | B19: HSBC Holdings plc | C19: Banking | D19: UK | E19: 45781.771 | F19: 46517.771 | G19: Interest Rate Swap | H19: 8000000 | I19: -215172 | J19: 0.00079 | K19: 0.481 | L19: 240000 | M19: 1800000000 | N19: 240000 | O19: 0.00013333333
A20: CP003 | B20: HSBC Holdings plc | C20: Banking | D20: UK | E20: 45853.771 | F20: 46673.771 | G20: Credit Default Swap | H20: 362000000 | I20: -9360195 | J20: 0.00076 | K20: 0.571 | L20: 18100000 | M20: 1800000000 | N20: 18100000 | O20: 0.010055556
A21: CP003 | B21: HSBC Holdings plc | C21: Banking | D21: UK | E21: 45816.771 | F21: 46524.771 | G21: Senior Unsecured Bond | H21: 468000000 | I21: N/A | J21: 0.0008 | K21: 0.5296 | L21: 468000000 | M21: 1800000000 | N21: 468000000 | O21: 0.26
A22: CP003 | B22: HSBC Holdings plc | C22: Banking | D22: UK | E22: 45973.771 | F22: 46589.771 | G22: Interest Rate Swap | H22: 482000000 | I22: -12291625 | J22: 0.00075 | K22: 0.4795 | L22: 14460000 | M22: 1800000000 | N22: 14460000 | O22: 0.0080333333
A23: CP004 | B23: Citibank N.A. | C23: Banking | D23: US | E23: 45670.771 | F23: 46711.771 | G23: Trade Finance LC | H23: 385000000 | I23: N/A | J23: 0.00204 | K23: 0.359 | L23: 192500000 | M23: 1200000000 | N23: 192500000 | O23: 0.16041667
A24: CP004 | B24: Citibank N.A. | C24: Banking | D24: US | E24: 45939.771 | F24: 46911.771 | G24: Revolving Credit Fac. | H24: 398000000 | I24: N/A | J24: 0.00215 | K24: 0.4286 | L24: 298500000 | M24: 1200000000 | N24: 298500000 | O24: 0.24875
A25: CP004 | B25: Citibank N.A. | C25: Banking | D25: US | E25: 45873.771 | F25: 46269.771 | G25: Senior Secured Loan | H25: 411000000 | I25: N/A | J25: 0.00171 | K25: 0.2768 | L25: 411000000 | M25: 1200000000 | N25: 411000000 | O25: 0.3425
A26: CP004 | B26: Citibank N.A. | C26: Banking | D26: US | E26: 45797.771 | F26: 46483.771 | G26: Trade Finance LC | H26: 476000000 | I26: N/A | J26: 0.00189 | K26: 0.3888 | L26: 238000000 | M26: 1200000000 | N26: 238000000 | O26: 0.19833333
A27: CP004 | B27: Citibank N.A. | C27: Banking | D27: US | E27: 45820.771 | F27: 46767.771 | G27: Revolving Credit Fac. | H27: 288000000 | I27: N/A | J27: 0.00175 | K27: 0.3218 | L27: 216000000 | M27: 1200000000 | N27: 216000000 | O27: 0.18
A28: CP005 | B28: Goldman Sachs International | C28: Inv. Banking | D28: US | E28: 45707.771 | F28: 46199.771 | G28: Interest Rate Swap | H28: 167000000 | I28: 703830 | J28: 0.00135 | K28: 0.3662 | L28: 5010000 | M28: 1000000000 | N28: 5010000 | O28: 0.00501
A29: CP005 | B29: Goldman Sachs International | C29: Inv. Banking | D29: US | E29: 45664.771 | F29: 46580.771 | G29: Credit Default Swap | H29: 105000000 | I29: 872653 | J29: 0.00136 | K29: 0.4912 | L29: 5250000 | M29: 1000000000 | N29: 5250000 | O29: 0.00525
A30: CP005 | B30: Goldman Sachs International | C30: Inv. Banking | D30: US | E30: 45895.771 | F30: 46968.771 | G30: Senior Unsecured Bond | H30: 201000000 | I30: N/A | J30: 0.00134 | K30: 0.4906 | L30: 201000000 | M30: 1000000000 | N30: 201000000 | O30: 0.201
A31: CP005 | B31: Goldman Sachs International | C31: Inv. Banking | D31: US | E31: 45973.771 | F31: 46666.771 | G31: Interest Rate Swap | H31: 369000000 | I31: -5353324 | J31: 0.00145 | K31: 0.3561 | L31: 11070000 | M31: 1000000000 | N31: 11070000 | O31: 0.01107
A32: CP005 | B32: Goldman Sachs International | C32: Inv. Banking | D32: US | E32: 45857.771 | F32: 46778.771 | G32: Credit Default Swap | H32: 100000000 | I32: 1444789 | J32: 0.00171 | K32: 0.5528 | L32: 5000000 | M32: 1000000000 | N32: 5000000 | O32: 0.005
A33: CP006 | B33: Mitsubishi UFJ Financial | C33: Banking | D33: Japan | E33: 45874.771 | F33: 46590.771 | G33: Revolving Credit Fac. | H33: 70000000 | I33: N/A | J33: 0.00239 | K33: 0.3165 | L33: 52500000 | M33: 900000000 | N33: 52500000 | O33: 0.058333333
A34: CP006 | B34: Mitsubishi UFJ Financial | C34: Banking | D34: Japan | E34: 45796.771 | F34: 46236.771 | G34: Senior Secured Loan | H34: 22000000 | I34: N/A | J34: 0.0028 | K34: 0.3001 | L34: 22000000 | M34: 900000000 | N34: 22000000 | O34: 0.024444444
A35: CP006 | B35: Mitsubishi UFJ Financial | C35: Banking | D35: Japan | E35: 45986.771 | F35: 46618.771 | G35: Trade Finance LC | H35: 310000000 | I35: N/A | J35: 0.0024 | K35: 0.3949 | L35: 155000000 | M35: 900000000 | N35: 155000000 | O35: 0.17222222
A36: CP006 | B36: Mitsubishi UFJ Financial | C36: Banking | D36: Japan | E36: 46003.771 | F36: 46518.771 | G36: Revolving Credit Fac. | H36: 325000000 | I36: N/A | J36: 0.0023 | K36: 0.321 | L36: 243750000 | M36: 900000000 | N36: 243750000 | O36: 0.27083333
A37: CP006 | B37: Mitsubishi UFJ Financial | C37: Banking | D37: Japan | E37: 45662.771 | F37: 46252.771 | G37: Senior Secured Loan | H37: 366000000 | I37: N/A | J37: 0.0026 | K37: 0.2406 | L37: 366000000 | M37: 900000000 | N37: 366000000 | O37: 0.40666667
A38: CP007 | B38: Apple Inc | C38: Technology | D38: US | E38: 45719.771 | F38: 46583.771 | G38: Credit Default Swap | H38: 204000000 | I38: 1405843 | J38: 0.0002 | K38: 0.4904 | L38: 10200000 | M38: 500000000 | N38: 10200000 | O38: 0.0204
A39: CP007 | B39: Apple Inc | C39: Technology | D39: US | E39: 45707.771 | F39: 46649.771 | G39: Senior Unsecured Bond | H39: 198000000 | I39: N/A | J39: 0.0002 | K39: 0.4585 | L39: 198000000 | M39: 500000000 | N39: 198000000 | O39: 0.396
A40: CP007 | B40: Apple Inc | C40: Technology | D40: US | E40: 45822.771 | F40: 46421.771 | G40: Interest Rate Swap | H40: 365000000 | I40: 6116061 | J40: 0.00017 | K40: 0.4277 | L40: 10950000 | M40: 500000000 | N40: 10950000 | O40: 0.0219
A41: CP007 | B41: Apple Inc | C41: Technology | D41: US | E41: 45696.771 | F41: 46274.771 | G41: Credit Default Swap | H41: 197000000 | I41: 2302052 | J41: 0.00021 | K41: 0.4697 | L41: 9850000 | M41: 500000000 | N41: 9850000 | O41: 0.0197
A42: CP007 | B42: Apple Inc | C42: Technology | D42: US | E42: 45749.771 | F42: 46208.771 | G42: Senior Unsecured Bond | H42: 158000000 | I42: N/A | J42: 0.00023 | K42: 0.51 | L42: 158000000 | M42: 500000000 | N42: 158000000 | O42: 0.316
A43: CP008 | B43: Shell plc | C43: Energy | D43: UK | E43: 45659.771 | F43: 46095.771 | G43: Senior Secured Loan | H43: 125000000 | I43: N/A | J43: 0.00066 | K43: 0.3379 | L43: 125000000 | M43: 750000000 | N43: 125000000 | O43: 0.16666667
A44: CP008 | B44: Shell plc | C44: Energy | D44: UK | E44: 45697.771 | F44: 46753.771 | G44: Trade Finance LC | H44: 388000000 | I44: N/A | J44: 0.00054 | K44: 0.3793 | L44: 194000000 | M44: 750000000 | N44: 194000000 | O44: 0.25866667
A45: CP008 | B45: Shell plc | C45: Energy | D45: UK | E45: 45679.771 | F45: 46121.771 | G45: Revolving Credit Fac. | H45: 207000000 | I45: N/A | J45: 0.00064 | K45: 0.3238 | L45: 155250000 | M45: 750000000 | N45: 155250000 | O45: 0.207
A46: CP008 | B46: Shell plc | C46: Energy | D46: UK | E46: 45873.771 | F46: 46627.771 | G46: Senior Secured Loan | H46: 424000000 | I46: N/A | J46: 0.00058 | K46: 0.2389 | L46: 424000000 | M46: 750000000 | N46: 424000000 | O46: 0.56533333
A47: CP008 | B47: Shell plc | C47: Energy | D47: UK | E47: 45770.771 | F47: 46705.771 | G47: Trade Finance LC | H47: 122000000 | I47: N/A | J47: 0.00063 | K47: 0.2602 | L47: 61000000 | M47: 750000000 | N47: 61000000 | O47: 0.081333333
A48: CP009 | B48: AstraZeneca plc | C48: Healthcare | D48: UK | E48: 45951.771 | F48: 46687.771 | G48: Senior Unsecured Bond | H48: 476000000 | I48: N/A | J48: 0.00121 | K48: 0.4507 | L48: 476000000 | M48: 400000000 | N48: 476000000 | O48: 1.19
A49: CP009 | B49: AstraZeneca plc | C49: Healthcare | D49: UK | E49: 45698.771 | F49: 46790.771 | G49: Interest Rate Swap | H49: 447000000 | I49: 1370901 | J49: 0.00121 | K49: 0.4807 | L49: 13410000 | M49: 400000000 | N49: 13410000 | O49: 0.033525
A50: CP009 | B50: AstraZeneca plc | C50: Healthcare | D50: UK | E50: 45970.771 | F50: 46420.771 | G50: Credit Default Swap | H50: 253000000 | I50: 3085064 | J50: 0.00121 | K50: 0.553 | L50: 12650000 | M50: 400000000 | N50: 12650000 | O50: 0.031625
A51: CP009 | B51: AstraZeneca plc | C51: Healthcare | D51: UK | E51: 45721.771 | F51: 46802.771 | G51: Senior Unsecured Bond | H51: 32000000 | I51: N/A | J51: 0.00141 | K51: 0.479 | L51: 32000000 | M51: 400000000 | N51: 32000000 | O51: 0.08
A52: CP009 | B52: AstraZeneca plc | C52: Healthcare | D52: UK | E52: 45881.771 | F52: 46770.771 | G52: Interest Rate Swap | H52: 289000000 | I52: -8090132 | J52: 0.00141 | K52: 0.4333 | L52: 8670000 | M52: 400000000 | N52: 8670000 | O52: 0.021675
A53: CP010 | B53: Volkswagen AG | C53: Automotive | D53: Germany | E53: 45753.771 | F53: 46702.771 | G53: Trade Finance LC | H53: 101000000 | I53: N/A | J53: 0.00722 | K53: 0.2738 | L53: 50500000 | M53: 600000000 | N53: 50500000 | O53: 0.084166667
A54: CP010 | B54: Volkswagen AG | C54: Automotive | D54: Germany | E54: 45753.771 | F54: 46692.771 | G54: Revolving Credit Fac. | H54: 482000000 | I54: N/A | J54: 0.00589 | K54: 0.3137 | L54: 361500000 | M54: 600000000 | N54: 361500000 | O54: 0.6025
A55: CP010 | B55: Volkswagen AG | C55: Automotive | D55: Germany | E55: 45690.771 | F55: 46729.771 | G55: Senior Secured Loan | H55: 22000000 | I55: N/A | J55: 0.00698 | K55: 0.3114 | L55: 22000000 | M55: 600000000 | N55: 22000000 | O55: 0.036666667
A56: CP010 | B56: Volkswagen AG | C56: Automotive | D56: Germany | E56: 45711.771 | F56: 46454.771 | G56: Trade Finance LC | H56: 252000000 | I56: N/A | J56: 0.00619 | K56: 0.3037 | L56: 126000000 | M56: 600000000 | N56: 126000000 | O56: 0.21
A57: CP010 | B57: Volkswagen AG | C57: Automotive | D57: Germany | E57: 45701.771 | F57: 46592.771 | G57: Revolving Credit Fac. | H57: 284000000 | I57: N/A | J57: 0.00689 | K57: 0.3584 | L57: 213000000 | M57: 600000000 | N57: 213000000 | O57: 0.355
A58: CP011 | B58: Allianz SE | C58: Insurance | D58: Germany | E58: 45661.771 | F58: 46497.771 | G58: Interest Rate Swap | H58: 184000000 | I58: -344715 | J58: 0.00052 | K58: 0.4998 | L58: 5520000 | M58: 800000000 | N58: 5520000 | O58: 0.0069
A59: CP011 | B59: Allianz SE | C59: Insurance | D59: Germany | E59: 45754.771 | F59: 46389.771 | G59: Credit Default Swap | H59: 229000000 | I59: 3358011 | J59: 0.0006 | K59: 0.5365 | L59: 11450000 | M59: 800000000 | N59: 11450000 | O59: 0.0143125
A60: CP011 | B60: Allianz SE | C60: Insurance | D60: Germany | E60: 45942.771 | F60: 46506.771 | G60: Senior Unsecured Bond | H60: 342000000 | I60: N/A | J60: 0.00054 | K60: 0.5348 | L60: 342000000 | M60: 800000000 | N60: 342000000 | O60: 0.4275
A61: CP011 | B61: Allianz SE | C61: Insurance | D61: Germany | E61: 45718.771 | F61: 46325.771 | G61: Interest Rate Swap | H61: 499000000 | I61: -12212541 | J61: 0.00066 | K61: 0.404 | L61: 14970000 | M61: 800000000 | N61: 14970000 | O61: 0.0187125
A62: CP011 | B62: Allianz SE | C62: Insurance | D62: Germany | E62: 45999.771 | F62: 46652.771 | G62: Credit Default Swap | H62: 92000000 | I62: -2464609 | J62: 0.00057 | K62: 0.5164 | L62: 4600000 | M62: 800000000 | N62: 4600000 | O62: 0.00575
A63: CP012 | B63: Berkshire Hathaway Finance | C63: Insurance | D63: US | E63: 45991.771 | F63: 46424.771 | G63: Revolving Credit Fac. | H63: 410000000 | I63: N/A | J63: 0.00042 | K63: 0.3621 | L63: 307500000 | M63: 1000000000 | N63: 307500000 | O63: 0.3075
A64: CP012 | B64: Berkshire Hathaway Finance | C64: Insurance | D64: US | E64: 45839.771 | F64: 46898.771 | G64: Senior Secured Loan | H64: 204000000 | I64: N/A | J64: 0.00039 | K64: 0.2779 | L64: 204000000 | M64: 1000000000 | N64: 204000000 | O64: 0.204
A65: CP012 | B65: Berkshire Hathaway Finance | C65: Insurance | D65: US | E65: 45657.771 | F65: 46059.771 | G65: Trade Finance LC | H65: 52000000 | I65: N/A | J65: 0.00041 | K65: 0.3776 | L65: 26000000 | M65: 1000000000 | N65: 26000000 | O65: 0.026
A66: CP012 | B66: Berkshire Hathaway Finance | C66: Insurance | D66: US | E66: 45782.771 | F66: 46161.771 | G66: Revolving Credit Fac. | H66: 498000000 | I66: N/A | J66: 0.00035 | K66: 0.3461 | L66: 373500000 | M66: 1000000000 | N66: 373500000 | O66: 0.3735
A67: CP012 | B67: Berkshire Hathaway Finance | C67: Insurance | D67: US | E67: 45955.771 | F67: 46607.771 | G67: Senior Secured Loan | H67: 122000000 | I67: N/A | J67: 0.00038 | K67: 0.3002 | L67: 122000000 | M67: 1000000000 | N67: 122000000 | O67: 0.122
A68: CP013 | B68: Enel SpA | C68: Utilities | D68: Italy | E68: 45667.771 | F68: 46448.771 | G68: Credit Default Swap | H68: 97000000 | I68: 2238952 | J68: 0.00814 | K68: 0.4665 | L68: 4850000 | M68: 350000000 | N68: 4850000 | O68: 0.013857143
A69: CP013 | B69: Enel SpA | C69: Utilities | D69: Italy | E69: 45755.771 | F69: 46547.771 | G69: Senior Unsecured Bond | H69: 128000000 | I69: N/A | J69: 0.00933 | K69: 0.459 | L69: 128000000 | M69: 350000000 | N69: 128000000 | O69: 0.36571429
A70: CP013 | B70: Enel SpA | C70: Utilities | D70: Italy | E70: 45778.771 | F70: 46569.771 | G70: Interest Rate Swap | H70: 497000000 | I70: -6237009 | J70: 0.00928 | K70: 0.4212 | L70: 14910000 | M70: 350000000 | N70: 14910000 | O70: 0.0426
A71: CP013 | B71: Enel SpA | C71: Utilities | D71: Italy | E71: 45952.771 | F71: 46369.771 | G71: Credit Default Swap | H71: 118000000 | I71: -812222 | J71: 0.00977 | K71: 0.5935 | L71: 5900000 | M71: 350000000 | N71: 5900000 | O71: 0.016857143
A72: CP013 | B72: Enel SpA | C72: Utilities | D72: Italy | E72: 45683.771 | F72: 46653.771 | G72: Senior Unsecured Bond | H72: 147000000 | I72: N/A | J72: 0.00946 | K72: 0.5186 | L72: 147000000 | M72: 350000000 | N72: 147000000 | O72: 0.42
A73: CP014 | B73: Tesco PLC | C73: Retail | D73: UK | E73: 45844.771 | F73: 46810.771 | G73: Senior Secured Loan | H73: 432000000 | I73: N/A | J73: 0.00829 | K73: 0.2496 | L73: 432000000 | M73: 200000000 | N73: 432000000 | O73: 2.16
A74: CP014 | B74: Tesco PLC | C74: Retail | D74: UK | E74: 45720.771 | F74: 46125.771 | G74: Trade Finance LC | H74: 225000000 | I74: N/A | J74: 0.00866 | K74: 0.2952 | L74: 112500000 | M74: 200000000 | N74: 112500000 | O74: 0.5625
A75: CP014 | B75: Tesco PLC | C75: Retail | D75: UK | E75: 45980.771 | F75: 46449.771 | G75: Revolving Credit Fac. | H75: 173000000 | I75: N/A | J75: 0.00779 | K75: 0.3531 | L75: 129750000 | M75: 200000000 | N75: 129750000 | O75: 0.64875
A76: CP014 | B76: Tesco PLC | C76: Retail | D76: UK | E76: 45671.771 | F76: 46064.771 | G76: Senior Secured Loan | H76: 266000000 | I76: N/A | J76: 0.00817 | K76: 0.3414 | L76: 266000000 | M76: 200000000 | N76: 266000000 | O76: 1.33
A77: CP014 | B77: Tesco PLC | C77: Retail | D77: UK | E77: 45809.771 | F77: 46413.771 | G77: Trade Finance LC | H77: 453000000 | I77: N/A | J77: 0.0094 | K77: 0.2528 | L77: 226500000 | M77: 200000000 | N77: 226500000 | O77: 1.1325
A78: CP015 | B78: TotalEnergies SE | C78: Energy | D78: France | E78: 45850.771 | F78: 46251.771 | G78: Senior Unsecured Bond | H78: 258000000 | I78: N/A | J78: 0.00146 | K78: 0.4483 | L78: 258000000 | M78: 700000000 | N78: 258000000 | O78: 0.36857143
A79: CP015 | B79: TotalEnergies SE | C79: Energy | D79: France | E79: 45938.771 | F79: 46374.771 | G79: Interest Rate Swap | H79: 239000000 | I79: -789772 | J79: 0.00147 | K79: 0.3791 | L79: 7170000 | M79: 700000000 | N79: 7170000 | O79: 0.010242857
A80: CP015 | B80: TotalEnergies SE | C80: Energy | D80: France | E80: 45874.771 | F80: 46633.771 | G80: Credit Default Swap | H80: 413000000 | I80: -9312650 | J80: 0.00115 | K80: 0.4834 | L80: 20650000 | M80: 700000000 | N80: 20650000 | O80: 0.0295
A81: CP015 | B81: TotalEnergies SE | C81: Energy | D81: France | E81: 45846.771 | F81: 46938.771 | G81: Senior Unsecured Bond | H81: 443000000 | I81: N/A | J81: 0.00131 | K81: 0.4082 | L81: 443000000 | M81: 700000000 | N81: 443000000 | O81: 0.63285714
A82: CP015 | B82: TotalEnergies SE | C82: Energy | D82: France | E82: 45828.771 | F82: 46410.771 | G82: Interest Rate Swap | H82: 357000000 | I82: 8264650 | J82: 0.00125 | K82: 0.4298 | L82: 10710000 | M82: 700000000 | N82: 10710000 | O82: 0.0153
A83: CP016 | B83: Roche Holding AG | C83: Healthcare | D83: Switzerland | E83: 45662.771 | F83: 46743.771 | G83: Trade Finance LC | H83: 15000000 | I83: N/A | J83: 0.00011 | K83: 0.3043 | L83: 7500000 | M83: 450000000 | N83: 7500000 | O83: 0.016666667
A84: CP016 | B84: Roche Holding AG | C84: Healthcare | D84: Switzerland | E84: 45741.771 | F84: 46232.771 | G84: Revolving Credit Fac. | H84: 71000000 | I84: N/A | J84: 0.00011 | K84: 0.4354 | L84: 53250000 | M84: 450000000 | N84: 53250000 | O84: 0.11833333
A85: CP016 | B85: Roche Holding AG | C85: Healthcare | D85: Switzerland | E85: 45735.771 | F85: 46397.771 | G85: Senior Secured Loan | H85: 29000000 | I85: N/A | J85: 0.0001 | K85: 0.2175 | L85: 29000000 | M85: 450000000 | N85: 29000000 | O85: 0.064444444
A86: CP016 | B86: Roche Holding AG | C86: Healthcare | D86: Switzerland | E86: 45689.771 | F86: 46219.771 | G86: Trade Finance LC | H86: 187000000 | I86: N/A | J86: 0.00011 | K86: 0.2729 | L86: 93500000 | M86: 450000000 | N86: 93500000 | O86: 0.20777778
A87: CP016 | B87: Roche Holding AG | C87: Healthcare | D87: Switzerland | E87: 45918.771 | F87: 46993.771 | G87: Revolving Credit Fac. | H87: 209000000 | I87: N/A | J87: 0.00011 | K87: 0.3564 | L87: 156750000 | M87: 450000000 | N87: 156750000 | O87: 0.34833333
A88: CP017 | B88: Vodafone Group PLC | C88: Telecom | D88: UK | E88: 45949.771 | F88: 46756.771 | G88: Interest Rate Swap | H88: 272000000 | I88: -1087377 | J88: 0.01335 | K88: 0.3696 | L88: 8160000 | M88: 300000000 | N88: 8160000 | O88: 0.0272
A89: CP017 | B89: Vodafone Group PLC | C89: Telecom | D89: UK | E89: 45940.771 | F89: 46317.771 | G89: Credit Default Swap | H89: 259000000 | I89: -3324169 | J89: 0.01352 | K89: 0.4987 | L89: 12950000 | M89: 300000000 | N89: 12950000 | O89: 0.043166667
A90: CP017 | B90: Vodafone Group PLC | C90: Telecom | D90: UK | E90: 45721.771 | F90: 46713.771 | G90: Senior Unsecured Bond | H90: 413000000 | I90: N/A | J90: 0.01161 | K90: 0.4752 | L90: 413000000 | M90: 300000000 | N90: 413000000 | O90: 1.3766667
A91: CP017 | B91: Vodafone Group PLC | C91: Telecom | D91: UK | E91: 45679.771 | F91: 46461.771 | G91: Interest Rate Swap | H91: 114000000 | I91: 2673034 | J91: 0.01219 | K91: 0.4401 | L91: 3420000 | M91: 300000000 | N91: 3420000 | O91: 0.0114
A92: CP017 | B92: Vodafone Group PLC | C92: Telecom | D92: UK | E92: 45850.771 | F92: 46389.771 | G92: Credit Default Swap | H92: 465000000 | I92: -9855148 | J92: 0.01276 | K92: 0.4047 | L92: 23250000 | M92: 300000000 | N92: 23250000 | O92: 0.0775
A93: CP018 | B93: Rio Tinto PLC | C93: Mining | D93: UK | E93: 45777.771 | F93: 46283.771 | G93: Revolving Credit Fac. | H93: 490000000 | I93: N/A | J93: 0.00224 | K93: 0.3232 | L93: 367500000 | M93: 500000000 | N93: 367500000 | O93: 0.735
A94: CP018 | B94: Rio Tinto PLC | C94: Mining | D94: UK | E94: 45725.771 | F94: 46341.771 | G94: Senior Secured Loan | H94: 385000000 | I94: N/A | J94: 0.00252 | K94: 0.2432 | L94: 385000000 | M94: 500000000 | N94: 385000000 | O94: 0.77
A95: CP018 | B95: Rio Tinto PLC | C95: Mining | D95: UK | E95: 45968.771 | F95: 46617.771 | G95: Trade Finance LC | H95: 117000000 | I95: N/A | J95: 0.00239 | K95: 0.343 | L95: 58500000 | M95: 500000000 | N95: 58500000 | O95: 0.117
A96: CP018 | B96: Rio Tinto PLC | C96: Mining | D96: UK | E96: 45737.771 | F96: 46296.771 | G96: Revolving Credit Fac. | H96: 75000000 | I96: N/A | J96: 0.00206 | K96: 0.3098 | L96: 56250000 | M96: 500000000 | N96: 56250000 | O96: 0.1125
A97: CP018 | B97: Rio Tinto PLC | C97: Mining | D97: UK | E97: 45732.771 | F97: 46232.771 | G97: Senior Secured Loan | H97: 423000000 | I97: N/A | J97: 0.00197 | K97: 0.2525 | L97: 423000000 | M97: 500000000 | N97: 423000000 | O97: 0.846
A98: CP019 | B98: Stellantis N.V. | C98: Automotive | D98: Netherlands | E98: 45961.771 | F98: 46882.771 | G98: Credit Default Swap | H98: 153000000 | I98: 4162803 | J98: 0.00731 | K98: 0.4003 | L98: 7650000 | M98: 400000000 | N98: 7650000 | O98: 0.019125
A99: CP019 | B99: Stellantis N.V. | C99: Automotive | D99: Netherlands | E99: 45999.771 | F99: 46816.771 | G99: Senior Unsecured Bond | H99: 131000000 | I99: N/A | J99: 0.00907 | K99: 0.4978 | L99: 131000000 | M99: 400000000 | N99: 131000000 | O99: 0.3275
A100: CP019 | B100: Stellantis N.V. | C100: Automotive | D100: Netherlands | E100: 45800.771 | F100: 46472.771 | G100: Interest Rate Swap | H100: 67000000 | I100: -1801860 | J100: 0.00882 | K100: 0.4611 | L100: 2010000 | M100: 400000000 | N100: 2010000 | O100: 0.005025
A101: CP019 | B101: Stellantis N.V. | C101: Automotive | D101: Netherlands | E101: 45939.771 | F101: 46322.771 | G101: Credit Default Swap | H101: 85000000 | I101: 173193 | J101: 0.00844 | K101: 0.4615 | L101: 4250000 | M101: 400000000 | N101: 4250000 | O101: 0.010625
A102: CP019 | B102: Stellantis N.V. | C102: Automotive | D102: Netherlands | E102: 45869.771 | F102: 46774.771 | G102: Senior Unsecured Bond | H102: 161000000 | I102: N/A | J102: 0.00816 | K102: 0.5076 | L102: 161000000 | M102: 400000000 | N102: 161000000 | O102: 0.4025
...

Sheet Rating Migration Matrix
A1: 1-YEAR RATING MIGRATION MATRIX — MOODY'S SCALE (2023 ANNUAL STUDY)
A2: Source: | B2: Moody's Annual Default & Rating Transition Study 2023
A3: Usage: | B3: Internal credit migration scenario modelling — restricted, not for external distribution
A4: Row = Starting Rating | Column = Ending Rating | Values = 1-year transition probability
A6: From \ To | B6: AAA | C6: AA | D6: A | E6: BBB | F6: BB | G6: B | H6: CCC | I6: D (Default) | J6: Row Sum
A7: AAA | B7: 0.9241 | C7: 0.0634 | D7: 0.006 | E7: 0.0013 | F7: 0.0006 | G7: 0.0003 | H7: 0.0002 | I7: 0.0001 | J7: =SUM(B7:I7)
A8: AA | B8: 0.0072 | C8: 0.9072 | D8: 0.077 | E8: 0.0058 | F8: 0.0013 | G8: 0.0009 | H8: 0.0002 | I8: 0.0004 | J8: =SUM(B8:I8)
A9: A | B9: 0.0009 | C9: 0.0222 | D9: 0.9078 | E9: 0.0603 | F9: 0.0063 | G9: 0.0017 | H9: 0.0003 | I9: 0.0005 | J9: =SUM(B9:I9)
A10: BBB | B10: 0.0004 | C10: 0.0034 | D10: 0.0541 | E10: 0.879 | F10: 0.0493 | G10: 0.0105 | H10: 0.0019 | I10: 0.0014 | J10: =SUM(B10:I10)
A11: BB | B11: 0.0003 | C11: 0.0013 | D11: 0.0068 | E11: 0.0687 | F11: 0.801 | G11: 0.0985 | H11: 0.0122 | I11: 0.0112 | J11: =SUM(B11:I11)
A12: B | B12: 0.0001 | C12: 0.0006 | D12: 0.005 | E12: 0.015 | F12: 0.078 | G12: 0.8154 | H12: 0.0629 | I12: 0.023 | J12: =SUM(B12:I12)
A13: CCC | B13: 0.0001 | C13: 0.0003 | D13: 0.0023 | E13: 0.0065 | F13: 0.0182 | G13: 0.0989 | H13: 0.6279 | I13: 0.2458 | J13: =SUM(B13:I13)
A14: D (Default) | B14: 0 | C14: 0 | D14: 0 | E14: 0 | F14: 0 | G14: 0 | H14: 0 | I14: 1 | J14: =SUM(B14:I14)
A16: Note: Row sums should equal 100.00%. Diagonal entries (shaded) represent probability of rating stability.

Sheet Sector Concentration
A1: CREDIT EXPOSURE BY SECTOR — Q3 2026 SUMMARY
A2: Source: Credit Exposure Register (live SUMIF/COUNTIF — auto-recalculates on workbook open)
B4: Volume Metrics | E4: Risk Indicators
A5: Sector | B5: Trade Count | C5: Total Notional USD | D5: Total EAD USD | E5: Avg PD 1Y | F5: Avg LGD | G5: Exposure Share %
A6: Banking | B6: =COUNTIF('Credit Exposure Register'!C:C,"Banking") | C6: =SUMIF('Credit Exposure Register'!C:C,"Banking",'Credit Exposure Register'!H:H) | D6: =SUMIF('Credit Exposure Register'!C:C,"Banking",'Credit Exposure Register'!L:L) | E6: =AVERAGEIF('Credit Exposure Register'!C:C,"Banking",'Credit Exposure Register'!J:J) | F6: =AVERAGEIF('Credit Exposure Register'!C:C,"Banking",'Credit Exposure Register'!K:K) | G6: =D6/SUM($D$6:$D$16)
A7: Inv. Banking | B7: =COUNTIF('Credit Exposure Register'!C:C,"Inv. Banking") | C7: =SUMIF('Credit Exposure Register'!C:C,"Inv. Banking",'Credit Exposure Register'!H:H) | D7: =SUMIF('Credit Exposure Register'!C:C,"Inv. Banking",'Credit Exposure Register'!L:L) | E7: =AVERAGEIF('Credit Exposure Register'!C:C,"Inv. Banking",'Credit Exposure Register'!J:J) | F7: =AVERAGEIF('Credit Exposure Register'!C:C,"Inv. Banking",'Credit Exposure Register'!K:K) | G7: =D7/SUM($D$6:$D$16)
A8: Technology | B8: =COUNTIF('Credit Exposure Register'!C:C,"Technology") | C8: =SUMIF('Credit Exposure Register'!C:C,"Technology",'Credit Exposure Register'!H:H) | D8: =SUMIF('Credit Exposure Register'!C:C,"Technology",'Credit Exposure Register'!L:L) | E8: =AVERAGEIF('Credit Exposure Register'!C:C,"Technology",'Credit Exposure Register'!J:J) | F8: =AVERAGEIF('Credit Exposure Register'!C:C,"Technology",'Credit Exposure Register'!K:K) | G8: =D8/SUM($D$6:$D$16)
A9: Energy | B9: =COUNTIF('Credit Exposure Register'!C:C,"Energy") | C9: =SUMIF('Credit Exposure Register'!C:C,"Energy",'Credit Exposure Register'!H:H) | D9: =SUMIF('Credit Exposure Register'!C:C,"Energy",'Credit Exposure Register'!L:L) | E9: =AVERAGEIF('Credit Exposure Register'!C:C,"Energy",'Credit Exposure Register'!J:J) | F9: =AVERAGEIF('Credit Exposure Register'!C:C,"Energy",'Credit Exposure Register'!K:K) | G9: =D9/SUM($D$6:$D$16)
A10: Healthcare | B10: =COUNTIF('Credit Exposure Register'!C:C,"Healthcare") | C10: =SUMIF('Credit Exposure Register'!C:C,"Healthcare",'Credit Exposure Register'!H:H) | D10: =SUMIF('Credit Exposure Register'!C:C,"Healthcare",'Credit Exposure Register'!L:L) | E10: =AVERAGEIF('Credit Exposure Register'!C:C,"Healthcare",'Credit Exposure Register'!J:J) | F10: =AVERAGEIF('Credit Exposure Register'!C:C,"Healthcare",'Credit Exposure Register'!K:K) | G10: =D10/SUM($D$6:$D$16)
A11: Automotive | B11: =COUNTIF('Credit Exposure Register'!C:C,"Automotive") | C11: =SUMIF('Credit Exposure Register'!C:C,"Automotive",'Credit Exposure Register'!H:H) | D11: =SUMIF('Credit Exposure Register'!C:C,"Automotive",'Credit Exposure Register'!L:L) | E11: =AVERAGEIF('Credit Exposure Register'!C:C,"Automotive",'Credit Exposure Register'!J:J) | F11: =AVERAGEIF('Credit Exposure Register'!C:C,"Automotive",'Credit Exposure Register'!K:K) | G11: =D11/SUM($D$6:$D$16)
A12: Insurance | B12: =COUNTIF('Credit Exposure Register'!C:C,"Insurance") | C12: =SUMIF('Credit Exposure Register'!C:C,"Insurance",'Credit Exposure Register'!H:H) | D12: =SUMIF('Credit Exposure Register'!C:C,"Insurance",'Credit Exposure Register'!L:L) | E12: =AVERAGEIF('Credit Exposure Register'!C:C,"Insurance",'Credit Exposure Register'!J:J) | F12: =AVERAGEIF('Credit Exposure Register'!C:C,"Insurance",'Credit Exposure Register'!K:K) | G12: =D12/SUM($D$6:$D$16)
A13: Utilities | B13: =COUNTIF('Credit Exposure Register'!C:C,"Utilities") | C13: =SUMIF('Credit Exposure Register'!C:C,"Utilities",'Credit Exposure Register'!H:H) | D13: =SUMIF('Credit Exposure Register'!C:C,"Utilities",'Credit Exposure Register'!L:L) | E13: =AVERAGEIF('Credit Exposure Register'!C:C,"Utilities",'Credit Exposure Register'!J:J) | F13: =AVERAGEIF('Credit Exposure Register'!C:C,"Utilities",'Credit Exposure Register'!K:K) | G13: =D13/SUM($D$6:$D$16)
A14: Retail | B14: =COUNTIF('Credit Exposure Register'!C:C,"Retail") | C14: =SUMIF('Credit Exposure Register'!C:C,"Retail",'Credit Exposure Register'!H:H) | D14: =SUMIF('Credit Exposure Register'!C:C,"Retail",'Credit Exposure Register'!L:L) | E14: =AVERAGEIF('Credit Exposure Register'!C:C,"Retail",'Credit Exposure Register'!J:J) | F14: =AVERAGEIF('Credit Exposure Register'!C:C,"Retail",'Credit Exposure Register'!K:K) | G14: =D14/SUM($D$6:$D$16)
A15: Telecom | B15: =COUNTIF('Credit Exposure Register'!C:C,"Telecom") | C15: =SUMIF('Credit Exposure Register'!C:C,"Telecom",'Credit Exposure Register'!H:H) | D15: =SUMIF('Credit Exposure Register'!C:C,"Telecom",'Credit Exposure Register'!L:L) | E15: =AVERAGEIF('Credit Exposure Register'!C:C,"Telecom",'Credit Exposure Register'!J:J) | F15: =AVERAGEIF('Credit Exposure Register'!C:C,"Telecom",'Credit Exposure Register'!K:K) | G15: =D15/SUM($D$6:$D$16)
A16: Mining | B16: =COUNTIF('Credit Exposure Register'!C:C,"Mining") | C16: =SUMIF('Credit Exposure Register'!C:C,"Mining",'Credit Exposure Register'!H:H) | D16: =SUMIF('Credit Exposure Register'!C:C,"Mining",'Credit Exposure Register'!L:L) | E16: =AVERAGEIF('Credit Exposure Register'!C:C,"Mining",'Credit Exposure Register'!J:J) | F16: =AVERAGEIF('Credit Exposure Register'!C:C,"Mining",'Credit Exposure Register'!K:K) | G16: =D16/SUM($D$6:$D$16)
A17: TOTAL | B17: =SUM(B6:B16) | C17: =SUM(C6:C16) | D17: =SUM(D6:D16) | G17: =SUM(G6:G16)
A19: * Avg PD and Avg LGD use AVERAGEIF — sectors with zero trades show #DIV/0 (expected, not an error)

Sheet Counterparty Master
A1: COUNTERPARTY MASTER — APPROVED CREDIT COUNTERPARTIES
A2: Last Review Date: | B2: 46235 | D2: Approved By: | E2: Credit Committee | H2: Next Review: | I2: 46419
A4: CP ID | B4: Legal Name | C4: Short Name | D4: Sector | E4: Country | F4: Internal Rating | G4: External Rating | H4: Credit Limit USD | I4: Onboarding Date | J4: Status
A5: CP001 | B5: Deutsche Bank AG | C5: Deutsche | D5: Banking | E5: Germany | F5: AA- | G5: AA- | H5: 2000000000 | I5: 43100.771 | J5: ACTIVE
A6: CP002 | B6: BNP Paribas SA | C6: BNP | D6: Banking | E6: France | F6: A+ | G6: A+ | H6: 1500000000 | I6: 43131.771 | J6: ACTIVE
A7: CP003 | B7: HSBC Holdings plc | C7: HSBC | D7: Banking | E7: UK | F7: AA- | G7: AA- | H7: 1800000000 | I7: 43159.771 | J7: ACTIVE
A8: CP004 | B8: Citibank N.A. | C8: Citibank | D8: Banking | E8: US | F8: A | G8: A | H8: 1200000000 | I8: 43190.771 | J8: ACTIVE
A9: CP005 | B9: Goldman Sachs International | C9: Goldman | D9: Inv. Banking | E9: US | F9: A+ | G9: A+ | H9: 1000000000 | I9: 43220.771 | J9: ACTIVE
A10: CP006 | B10: Mitsubishi UFJ Financial | C10: Mitsubishi | D10: Banking | E10: Japan | F10: A- | G10: A- | H10: 900000000 | I10: 43616.771 | J10: ACTIVE
A11: CP007 | B11: Apple Inc | C11: Apple | D11: Technology | E11: US | F11: AAA | G11: AAA | H11: 500000000 | I11: 43646.771 | J11: ACTIVE
A12: CP008 | B12: Shell plc | C12: Shell | D12: Energy | E12: UK | F12: AA | G12: AA | H12: 750000000 | I12: 43677.771 | J12: ACTIVE
A13: CP009 | B13: AstraZeneca plc | C13: AstraZeneca | D13: Healthcare | E13: UK | F13: A+ | G13: A+ | H13: 400000000 | I13: 43708.771 | J13: ACTIVE
A14: CP010 | B14: Volkswagen AG | C14: Volkswagen | D14: Automotive | E14: Germany | F14: BBB+ | G14: BBB+ | H14: 600000000 | I14: 43738.771 | J14: REVIEW
A15: CP011 | B15: Allianz SE | C15: Allianz | D15: Insurance | E15: Germany | F15: AA | G15: AA | H15: 800000000 | I15: 44135.771 | J15: ACTIVE
A16: CP012 | B16: Berkshire Hathaway Finance | C16: Berkshire | D16: Insurance | E16: US | F16: AA+ | G16: AA+ | H16: 1000000000 | I16: 44165.771 | J16: ACTIVE
... A24: CP020 | B24: Westpac Banking Corp | C24: Westpac | D24: Banking | E24: Australia | F24: A- | G24: A- | H24: 600000000 | I24: 44408.771 | J24: ACTIVE

Sheet Risk Model Parameters
A1: CREDIT RISK MODEL PARAMETERS & GOVERNANCE RECORD
A2: All parameter changes require Credit Risk Committee approval and must be logged in the model change register.
A4: Parameter | B4: Value | C4: Unit | D4: Last Updated | E4: Approved By | F4: Notes
A5: VaR Confidence Level | B5: 99% | C5: Percent | D5: 46023 | E5: CRC-2026-01 | F5: Basel III minimum 99% for internal models approach (IMA)
A6: VaR Holding Period | B6: 10 | C6: Business Days | D6: 46023 | E6: CRC-2026-01 | F6: Regulatory capital square root of time scaling from 1-day VaR
A7: Credit VaR Horizon | B7: 1 | C7: Year | D7: 46023 | E7: CRC-2026-01 | F7: Annual horizon used for ICAAP credit VaR and stress testing
A8: PD Floor — Investment Grade | B8: 0.0300% | C8: Percent | D8: 46096 | E8: CRC-2026-07 | F8: Minimum PD for BBB- and above per CRR III Art. 160
A9: PD Floor — Sub-Investment Grade | B9: 0.1000% | C9: Percent | D9: 46096 | E9: CRC-2026-07 | F9: Minimum PD for BB+ and below per CRR III Art. 160
A10: LGD Floor — Senior Secured | B10: 20% | C10: Percent | D10: 46023 | E10: CRC-2026-01 | F10: F-IRB LGD floor for collateralised exposures
A11: LGD Floor — Senior Unsecured | B11: 45% | C11: Percent | D11: 46023 | E11: CRC-2026-01 | F11: F-IRB LGD for unsecured senior corporate per Basel
A12: Asset Correlation — Corporate | B12: 12%–24% | C12: Range | D12: 46023 | E12: CRC-2026-01 | F12: Basel III supervisory formula; higher for low-PD obligors
A13: Concentration Threshold | B13: 5% | C13: Percent | D13: 46174 | E13: CRC-2026-12 | F13: Sector concentration >5% of total EAD triggers capital add-on
A14: High Utilisation Threshold | B14: 80% | C14: Percent | D14: 46023 | E14: CRC-2026-01 | F14: Exposures >80% of limit trigger enhanced monitoring review
A15: Hard Limit Breach Threshold | B15: 100% | C15: Percent | D15: 46023 | E15: CRC-2026-01 | F15: >100% requires immediate escalation to CRO and CFO
A16: Migration Model Source | B16: Moody's 2023 | C16: N/A | D16: 46204 | E16: CRC-2026-15 | F16: Annual transition matrix — updated each July with Moody's new study
... A21: Recovery Rate — Corporate (Secured) | B21: 65% | C21: Percent | D21: 46023 | E21: CRC-2026-01 | F21: Senior secured recovery for corporate counterparties
A22: Model Next Validation Date | B22: 46477 | C22: Date | D22: 46266 | E22: CRC-2026-18 | F22: Annual model validation cycle — mandatory per SR 11-7 / SS1/23
